{
 "result":"success",
 "documentation":"https://www.exchangerate-api.com/docs",
 "terms_of_use":"https://www.exchangerate-api.com/terms",
 "time_last_update_unix":1749340801,
 "time_last_update_utc":"Sun, 08 Jun 2025 00:00:01 +0000",
 "time_next_update_unix":1749427201,
 "time_next_update_utc":"Mon, 09 Jun 2025 00:00:01 +0000",
 "base_code":"AUD",
 "conversion_rates":{
  "AUD":1,
  "AED":2.3852,
  "AFN":45.0847,
  "ALL":55.8472,
  "AMD":249.0610,
  "ANG":1.1626,
  "AOA":609.4435,
  "ARS":772.8781,
  "AWG":1.1626,
  "AZN":1.1036,
  "BAM":1.1136,
  "BBD":1.2990,
  "BDT":79.3277,
  "BGN":1.1135,
  "BHD":0.2442,
  "BIF":1923.4951,
  "BMD":0.6495,
  "BND":0.8366,
  "BOB":4.4875,
  "BRL":3.6263,
  "BSD":0.6495,
  "BTN":55.7267,
  "BWP":8.7042,
  "BYN":1.9717,
  "BZD":1.2990,
  "CAD":0.8888,
  "CDF":1886.8571,
  "CHF":0.5340,
  "CLP":604.2399,
  "CNY":4.6705,
  "COP":2656.9345,
  "CRC":329.6591,
  "CUP":15.5875,
  "CVE":62.7818,
  "CZK":14.1136,
  "DJF":115.4258,
  "DKK":4.2460,
  "DOP":38.2618,
  "DZD":85.3671,
  "EGP":32.2470,
  "ERN":9.7422,
  "ETB":88.2494,
  "EUR":0.5694,
  "FJD":1.4628,
  "FKP":0.4798,
  "FOK":4.2460,
  "GBP":0.4798,
  "GEL":1.7727,
  "GGP":0.4798,
  "GHS":7.0532,
  "GIP":0.4798,
  "GMD":47.2265,
  "GNF":5634.1623,
  "GTQ":4.9816,
  "GYD":135.2355,
  "HKD":5.0972,
  "HNL":16.8963,
  "HRK":4.2899,
  "HTG":84.5583,
  "HUF":229.4608,
  "IDR":10581.8503,
  "ILS":2.2742,
  "IMP":0.4798,
  "INR":55.7269,
  "IQD":846.6667,
  "IRR":27402.0156,
  "ISK":82.0825,
  "JEP":0.4798,
  "JMD":103.3924,
  "JOD":0.4605,
  "JPY":93.8110,
  "KES":83.9679,
  "KGS":56.6435,
  "KHR":2606.8421,
  "KID":1.0000,
  "KMF":280.1125,
  "KRW":882.4565,
  "KWD":0.1987,
  "KYD":0.5412,
  "KZT":331.3792,
  "LAK":14096.8160,
  "LBP":58128.2283,
  "LKR":194.2631,
  "LRD":129.2608,
  "LSL":11.5376,
  "LYD":3.5191,
  "MAD":5.9524,
  "MDL":11.1935,
  "MGA":2957.0149,
  "MKD":35.1538,
  "MMK":2166.0521,
  "MNT":2326.3883,
  "MOP":5.2501,
  "MRU":25.6865,
  "MUR":29.4831,
  "MVR":10.0193,
  "MWK":1134.9714,
  "MXN":12.4295,
  "MYR":2.7451,
  "MZN":41.4127,
  "NAD":11.5376,
  "NGN":1018.3547,
  "NIO":23.8546,
  "NOK":6.5603,
  "NPR":89.1627,
  "NZD":1.0785,
  "OMR":0.2497,
  "PAB":0.6495,
  "PEN":2.3642,
  "PGK":2.6951,
  "PHP":36.2139,
  "PKR":183.1632,
  "PLN":2.4384,
  "PYG":5204.1256,
  "QAR":2.3641,
  "RON":2.8700,
  "RSD":66.7203,
  "RUB":51.3964,
  "RWF":932.9348,
  "SAR":2.4355,
  "SBD":5.5204,
  "SCR":9.2912,
  "SDG":288.8047,
  "SEK":6.2423,
  "SGD":0.8366,
  "SHP":0.4798,
  "SLE":14.7497,
  "SLL":14749.7220,
  "SOS":369.6269,
  "SRD":23.7868,
  "SSP":3035.0791,
  "STN":13.9496,
  "SYP":8356.0976,
  "SZL":11.5376,
  "THB":21.2057,
  "TJS":6.5539,
  "TMT":2.2728,
  "TND":1.9121,
  "TOP":1.5262,
  "TRY":25.4823,
  "TTD":4.4039,
  "TVD":1.0000,
  "TWD":19.4130,
  "TZS":1719.0236,
  "UAH":26.8851,
  "UGX":2355.6692,
  "USD":0.6495,
  "UYU":27.0084,
  "UZS":8325.4006,
  "VES":64.3578,
  "VND":16943.1323,
  "VUV":77.9043,
  "WST":1.7803,
  "XAF":373.4834,
  "XCD":1.7536,
  "XCG":1.1626,
  "XDR":0.4762,
  "XOF":373.4834,
  "XPF":67.9443,
  "YER":157.9681,
  "ZAR":11.5413,
  "ZMW":16.3029,
  "ZWL":4.5074
 }
}