{
 "result":"success",
 "documentation":"https://www.exchangerate-api.com/docs",
 "terms_of_use":"https://www.exchangerate-api.com/terms",
 "time_last_update_unix":1744070401,
 "time_last_update_utc":"Tue, 08 Apr 2025 00:00:01 +0000",
 "time_next_update_unix":1744156801,
 "time_next_update_utc":"Wed, 09 Apr 2025 00:00:01 +0000",
 "base_code":"EUR",
 "conversion_rates":{
  "EUR":1,
  "AED":4.0150,
  "AFN":78.7571,
  "ALL":99.1605,
  "AMD":429.1249,
  "ANG":1.9569,
  "AOA":1027.7336,
  "ARS":1176.7080,
  "AUD":1.8191,
  "AWG":1.9569,
  "AZN":1.8647,
  "BAM":1.9558,
  "BBD":2.1865,
  "BDT":132.8793,
  "BGN":1.9558,
  "BHD":0.4111,
  "BIF":3278.1165,
  "BMD":1.0933,
  "BND":1.4762,
  "BOB":7.6002,
  "BRL":6.4379,
  "BSD":1.0933,
  "BTN":93.8741,
  "BWP":15.4796,
  "BYN":3.4703,
  "BZD":2.1865,
  "CAD":1.5568,
  "CDF":3185.3396,
  "CHF":0.9380,
  "CLP":1070.8958,
  "CNY":8.0113,
  "COP":4659.1077,
  "CRC":554.1593,
  "CUP":26.2382,
  "CVE":110.2650,
  "CZK":25.2123,
  "DJF":194.2952,
  "DKK":7.4627,
  "DOP":69.0812,
  "DZD":146.4065,
  "EGP":56.2970,
  "ERN":16.3989,
  "ETB":144.2569,
  "FJD":2.5588,
  "FKP":0.8565,
  "FOK":7.4626,
  "GBP":0.8565,
  "GEL":3.0204,
  "GGP":0.8565,
  "GHS":17.0840,
  "GIP":0.8565,
  "GMD":79.6278,
  "GNF":9549.8623,
  "GTQ":8.4641,
  "GYD":230.3179,
  "HKD":8.4997,
  "HNL":28.0827,
  "HRK":7.5345,
  "HTG":143.6180,
  "HUF":407.7174,
  "IDR":18077.7041,
  "ILS":4.1257,
  "IMP":0.8565,
  "INR":93.9362,
  "IQD":1436.7915,
  "IRR":46652.4117,
  "ISK":145.0305,
  "JEP":0.8565,
  "JMD":172.8015,
  "JOD":0.7751,
  "JPY":161.1795,
  "KES":141.9421,
  "KGS":95.4690,
  "KHR":4385.0130,
  "KID":1.8193,
  "KMF":491.9678,
  "KRW":1606.3788,
  "KWD":0.3368,
  "KYD":0.9110,
  "KZT":570.6556,
  "LAK":23903.2916,
  "LBP":97846.7273,
  "LKR":325.2273,
  "LRD":219.6515,
  "LSL":21.3670,
  "LYD":5.3076,
  "MAD":10.4472,
  "MDL":19.4101,
  "MGA":4968.3468,
  "MKD":61.6070,
  "MMK":3114.6573,
  "MNT":3825.2989,
  "MOP":8.7505,
  "MRU":43.7705,
  "MUR":49.2836,
  "MVR":16.9481,
  "MWK":1912.9101,
  "MXN":22.6087,
  "MYR":4.9024,
  "MZN":70.0471,
  "NAD":21.3670,
  "NGN":1697.6446,
  "NIO":40.3417,
  "NOK":11.9621,
  "NPR":150.1986,
  "NZD":1.9710,
  "OMR":0.4204,
  "PAB":1.0933,
  "PEN":4.0351,
  "PGK":4.4606,
  "PHP":62.7998,
  "PKR":306.7524,
  "PLN":4.2928,
  "PYG":8825.6590,
  "QAR":3.9795,
  "RON":4.9774,
  "RSD":117.1445,
  "RUB":94.1112,
  "RWF":1579.0808,
  "SAR":4.0997,
  "SBD":9.0381,
  "SCR":16.1149,
  "SDG":490.7645,
  "SEK":11.0036,
  "SGD":1.4762,
  "SHP":0.8565,
  "SLE":24.8369,
  "SLL":24835.4585,
  "SOS":627.5948,
  "SRD":40.3931,
  "SSP":4983.5849,
  "STN":24.5000,
  "SYP":14155.7444,
  "SZL":21.3670,
  "THB":37.9004,
  "TJS":11.9340,
  "TMT":3.8392,
  "TND":3.3630,
  "TOP":2.6109,
  "TRY":41.5700,
  "TTD":8.4042,
  "TVD":1.8193,
  "TWD":36.1032,
  "TZS":2926.4431,
  "UAH":45.0885,
  "UGX":4042.8721,
  "USD":1.0933,
  "UYU":46.3275,
  "UZS":14169.7566,
  "VES":80.0691,
  "VND":28176.9921,
  "VUV":133.6886,
  "WST":3.0287,
  "XAF":655.9570,
  "XCD":2.9518,
  "XCG":1.9569,
  "XDR":0.8228,
  "XOF":655.9570,
  "XPF":119.3320,
  "YER":269.4650,
  "ZAR":21.3547,
  "ZMW":30.6889,
  "ZWL":9.4599
 }
}