{
 "result":"success",
 "documentation":"https://www.exchangerate-api.com/docs",
 "terms_of_use":"https://www.exchangerate-api.com/terms",
 "time_last_update_unix":1784419201,
 "time_last_update_utc":"Sun, 19 Jul 2026 00:00:01 +0000",
 "time_next_update_unix":1784505601,
 "time_next_update_utc":"Mon, 20 Jul 2026 00:00:01 +0000",
 "base_code":"AUD",
 "conversion_rates":{
  "AUD":1,
  "AED":2.5644,
  "AFN":46.3617,
  "ALL":57.2581,
  "AMD":255.9344,
  "ANG":1.2499,
  "AOA":670.7401,
  "ARS":1033.5311,
  "AWG":1.2499,
  "AZN":1.1873,
  "BAM":1.1940,
  "BBD":1.3965,
  "BDT":86.0633,
  "BGN":1.1940,
  "BHD":0.2626,
  "BIF":2090.2913,
  "BMD":0.6983,
  "BND":0.9015,
  "BOB":7.4062,
  "BRL":3.5627,
  "BSD":0.6983,
  "BTN":67.2807,
  "BWP":10.0410,
  "BYN":2.0125,
  "BZD":1.3965,
  "CAD":0.9789,
  "CDF":1618.7970,
  "CHF":0.5631,
  "CLF":0.01633,
  "CLP":645.5495,
  "CNH":4.7315,
  "CNY":4.7310,
  "COP":2251.1375,
  "CRC":317.9348,
  "CUP":16.7586,
  "CVE":67.3169,
  "CZK":14.7675,
  "DJF":124.0980,
  "DKK":4.5546,
  "DOP":40.8751,
  "DZD":93.1527,
  "EGP":35.2745,
  "ERN":10.4741,
  "ETB":112.3695,
  "EUR":0.6105,
  "FJD":1.5640,
  "FKP":0.5191,
  "FOK":4.5546,
  "GBP":0.5191,
  "GEL":1.8366,
  "GGP":0.5191,
  "GHS":8.0849,
  "GIP":0.5191,
  "GMD":51.9173,
  "GNF":6130.9386,
  "GTQ":5.3399,
  "GYD":146.4626,
  "HKD":5.4734,
  "HNL":18.7370,
  "HRK":4.5998,
  "HTG":91.5002,
  "HUF":221.4161,
  "IDR":12533.6267,
  "ILS":2.1232,
  "IMP":0.5191,
  "INR":67.2811,
  "IQD":916.1702,
  "IRR":960994.7644,
  "ISK":87.5054,
  "JEP":0.5191,
  "JMD":110.8040,
  "JOD":0.4951,
  "JPY":113.4065,
  "KES":90.4311,
  "KGS":61.0320,
  "KHR":2832.8947,
  "KID":1.0000,
  "KMF":300.3467,
  "KRW":1037.2381,
  "KWD":0.2150,
  "KYD":0.5819,
  "KZT":329.3964,
  "LAK":15537.7154,
  "LBP":62495.5328,
  "LKR":234.7815,
  "LRD":126.6742,
  "LSL":11.5089,
  "LYD":4.4760,
  "MAD":6.5240,
  "MDL":12.2616,
  "MGA":3032.3944,
  "MKD":37.5340,
  "MMK":1473.0823,
  "MNT":2528.0782,
  "MOP":5.6376,
  "MRU":28.0960,
  "MUR":32.7745,
  "MVR":10.8276,
  "MWK":1220.2764,
  "MXN":12.2206,
  "MYR":2.8495,
  "MZN":44.5928,
  "NAD":11.5089,
  "NGN":957.6734,
  "NIO":25.7489,
  "NOK":6.7363,
  "NPR":107.6491,
  "NZD":1.1952,
  "OMR":0.2685,
  "PAB":0.6983,
  "PEN":2.3719,
  "PGK":3.1122,
  "PHP":43.0338,
  "PKR":194.1501,
  "PLN":2.6489,
  "PYG":4224.9416,
  "QAR":2.5417,
  "RON":3.1984,
  "RSD":71.6445,
  "RUB":54.6581,
  "RWF":1028.4955,
  "SAR":2.6185,
  "SBD":5.5645,
  "SCR":10.2939,
  "SDG":312.9360,
  "SEK":6.7348,
  "SGD":0.9015,
  "SHP":0.5191,
  "SLE":17.0085,
  "SLL":17008.5011,
  "SOS":400.1859,
  "SRD":26.5246,
  "SSP":3385.1997,
  "STN":14.9573,
  "SYP":85.3455,
  "SZL":11.5089,
  "THB":23.4677,
  "TJS":6.4295,
  "TMT":2.4402,
  "TND":2.0592,
  "TOP":1.6654,
  "TRY":32.9344,
  "TTD":4.7480,
  "TVD":1.0000,
  "TWD":22.6169,
  "TZS":1844.0989,
  "UAH":31.1610,
  "UGX":2585.9450,
  "USD":0.6983,
  "UYU":28.0974,
  "UZS":8467.4688,
  "VES":514.5828,
  "VND":18283.5110,
  "VUV":83.1602,
  "WST":1.8917,
  "XAF":400.4623,
  "XCD":1.8853,
  "XCG":1.2499,
  "XDR":0.5135,
  "XOF":400.4623,
  "XPF":72.8523,
  "YER":166.6105,
  "ZAR":11.5116,
  "ZMW":12.7038,
  "ZWG":18.6333,
  "ZWL":18.6333
 }
}