{
 "result":"success",
 "documentation":"https://www.exchangerate-api.com/docs",
 "terms_of_use":"https://www.exchangerate-api.com/terms",
 "time_last_update_unix":1757721601,
 "time_last_update_utc":"Sat, 13 Sep 2025 00:00:01 +0000",
 "time_next_update_unix":1757808001,
 "time_next_update_utc":"Sun, 14 Sep 2025 00:00:01 +0000",
 "base_code":"AUD",
 "conversion_rates":{
  "AUD":1,
  "AED":2.4409,
  "AFN":45.0702,
  "ALL":54.8592,
  "AMD":254.1732,
  "ANG":1.1897,
  "AOA":621.6535,
  "ARS":961.8521,
  "AWG":1.1897,
  "AZN":1.1276,
  "BAM":1.1083,
  "BBD":1.3293,
  "BDT":80.8410,
  "BGN":1.1083,
  "BHD":0.2499,
  "BIF":1975.3922,
  "BMD":0.6646,
  "BND":0.8525,
  "BOB":4.5734,
  "BRL":3.5824,
  "BSD":0.6646,
  "BTN":58.6834,
  "BWP":9.1687,
  "BYN":2.0921,
  "BZD":1.3293,
  "CAD":0.9203,
  "CDF":1918.9524,
  "CHF":0.5296,
  "CLP":632.6085,
  "CNY":4.7351,
  "COP":2586.3127,
  "CRC":333.1597,
  "CUP":15.9514,
  "CVE":62.4846,
  "CZK":13.7998,
  "DJF":118.1211,
  "DKK":4.2295,
  "DOP":42.1031,
  "DZD":85.8067,
  "EGP":31.9569,
  "ERN":9.9697,
  "ETB":94.9081,
  "EUR":0.5667,
  "FJD":1.4853,
  "FKP":0.4903,
  "FOK":4.2295,
  "GBP":0.4903,
  "GEL":1.7910,
  "GGP":0.4903,
  "GHS":8.5098,
  "GIP":0.4903,
  "GMD":48.6292,
  "GNF":5757.9892,
  "GTQ":5.0611,
  "GYD":138.2910,
  "HKD":5.1730,
  "HNL":17.3023,
  "HRK":4.2696,
  "HTG":86.5507,
  "HUF":221.8350,
  "IDR":10886.7438,
  "ILS":2.2151,
  "IMP":0.4903,
  "INR":58.6836,
  "IQD":864.7639,
  "IRR":28124.4092,
  "ISK":81.2016,
  "JEP":0.4903,
  "JMD":105.7777,
  "JOD":0.4712,
  "JPY":98.1295,
  "KES":85.7757,
  "KGS":58.0376,
  "KHR":2651.1842,
  "KID":1.0000,
  "KMF":278.7868,
  "KRW":924.9053,
  "KWD":0.2022,
  "KYD":0.5539,
  "KZT":358.7006,
  "LAK":14349.1450,
  "LBP":59485.5934,
  "LKR":200.3268,
  "LRD":123.0318,
  "LSL":11.5507,
  "LYD":3.5732,
  "MAD":5.9801,
  "MDL":11.0057,
  "MGA":2920.1449,
  "MKD":34.7488,
  "MMK":1388.0519,
  "MNT":2375.4617,
  "MOP":5.3269,
  "MRU":26.3799,
  "MUR":30.2415,
  "MVR":10.2091,
  "MWK":1158.0828,
  "MXN":12.2752,
  "MYR":2.7948,
  "MZN":42.3850,
  "NAD":11.5507,
  "NGN":998.4281,
  "NIO":24.3086,
  "NOK":6.5629,
  "NPR":93.8935,
  "NZD":1.1163,
  "OMR":0.2556,
  "PAB":0.6646,
  "PEN":2.3183,
  "PGK":2.7966,
  "PHP":37.9839,
  "PKR":188.5366,
  "PLN":2.4113,
  "PYG":4706.2596,
  "QAR":2.4193,
  "RON":2.8732,
  "RSD":66.3345,
  "RUB":55.7369,
  "RWF":964.7650,
  "SAR":2.4924,
  "SBD":5.4364,
  "SCR":9.9707,
  "SDG":295.4399,
  "SEK":6.2017,
  "SGD":0.8525,
  "SHP":0.4903,
  "SLE":15.5036,
  "SLL":15503.5734,
  "SOS":378.0300,
  "SRD":26.0189,
  "SSP":3121.8638,
  "STN":13.8836,
  "SYP":8684.6270,
  "SZL":11.5507,
  "THB":21.0846,
  "TJS":6.3055,
  "TMT":2.3261,
  "TND":1.9271,
  "TOP":1.5626,
  "TRY":27.4861,
  "TTD":4.4827,
  "TVD":1.0000,
  "TWD":20.1312,
  "TZS":1634.8852,
  "UAH":27.4040,
  "UGX":2324.9562,
  "USD":0.6646,
  "UYU":26.4196,
  "UZS":8207.6527,
  "VES":106.6408,
  "VND":17419.8369,
  "VUV":78.9013,
  "WST":1.8003,
  "XAF":371.7157,
  "XCD":1.7945,
  "XCG":1.1897,
  "XDR":0.4839,
  "XOF":371.7157,
  "XPF":67.6227,
  "YER":158.2426,
  "ZAR":11.5507,
  "ZMW":15.8309,
  "ZWL":17.7648
 }
}