{
 "result":"success",
 "documentation":"https://www.exchangerate-api.com/docs",
 "terms_of_use":"https://www.exchangerate-api.com/terms",
 "time_last_update_unix":1751328001,
 "time_last_update_utc":"Tue, 01 Jul 2025 00:00:01 +0000",
 "time_next_update_unix":1751414401,
 "time_next_update_utc":"Wed, 02 Jul 2025 00:00:01 +0000",
 "base_code":"EUR",
 "conversion_rates":{
  "EUR":1,
  "AED":4.3181,
  "AFN":82.2606,
  "ALL":98.0681,
  "AMD":450.6272,
  "ANG":2.1047,
  "AOA":1100.9118,
  "ARS":1403.9980,
  "AUD":1.7928,
  "AWG":2.1047,
  "AZN":1.9925,
  "BAM":1.9558,
  "BBD":2.3516,
  "BDT":143.3344,
  "BGN":1.9558,
  "BHD":0.4421,
  "BIF":3506.9118,
  "BMD":1.1758,
  "BND":1.4967,
  "BOB":8.1009,
  "BRL":6.4291,
  "BSD":1.1758,
  "BTN":100.6069,
  "BWP":15.6416,
  "BYN":3.6856,
  "BZD":2.3516,
  "CAD":1.6030,
  "CDF":3406.7143,
  "CHF":0.9349,
  "CLP":1099.7814,
  "CNY":8.4166,
  "COP":4754.8851,
  "CRC":591.2956,
  "CUP":28.2192,
  "CVE":110.2650,
  "CZK":24.7348,
  "DJF":208.9642,
  "DKK":7.4601,
  "DOP":69.6916,
  "DZD":151.6382,
  "EGP":58.1599,
  "ERN":17.6370,
  "ETB":158.2632,
  "FJD":2.6216,
  "FKP":0.8574,
  "FOK":7.4604,
  "GBP":0.8573,
  "GEL":3.1911,
  "GGP":0.8574,
  "GHS":12.5298,
  "GIP":0.8574,
  "GMD":85.2101,
  "GNF":10181.9922,
  "GTQ":9.0090,
  "GYD":245.1714,
  "HKD":9.2300,
  "HNL":30.6160,
  "HRK":7.5345,
  "HTG":153.5874,
  "HUF":399.5135,
  "IDR":19074.6757,
  "ILS":3.9691,
  "IMP":0.8574,
  "INR":100.6073,
  "IQD":1535.2146,
  "IRR":49748.6039,
  "ISK":142.1869,
  "JEP":0.8574,
  "JMD":186.9643,
  "JOD":0.8336,
  "JPY":169.4671,
  "KES":151.4554,
  "KGS":102.2869,
  "KHR":4706.6447,
  "KID":1.7925,
  "KMF":491.9678,
  "KRW":1589.7301,
  "KWD":0.3586,
  "KYD":0.9798,
  "KZT":610.2899,
  "LAK":25358.9759,
  "LBP":105234.0050,
  "LKR":351.8908,
  "LRD":234.3723,
  "LSL":20.8676,
  "LYD":6.3457,
  "MAD":10.5879,
  "MDL":19.7947,
  "MGA":5167.3408,
  "MKD":61.6560,
  "MMK":2462.8758,
  "MNT":4199.2730,
  "MOP":9.5068,
  "MRU":46.7039,
  "MUR":52.8695,
  "MVR":18.1014,
  "MWK":2043.1313,
  "MXN":22.1027,
  "MYR":4.9415,
  "MZN":74.8819,
  "NAD":20.8676,
  "NGN":1802.9147,
  "NIO":43.1192,
  "NOK":11.8658,
  "NPR":160.9710,
  "NZD":1.9338,
  "OMR":0.4521,
  "PAB":1.1758,
  "PEN":4.1613,
  "PGK":4.8298,
  "PHP":66.1871,
  "PKR":333.8767,
  "PLN":4.2433,
  "PYG":9370.0151,
  "QAR":4.2799,
  "RON":5.0788,
  "RSD":117.1797,
  "RUB":92.0999,
  "RWF":1696.8186,
  "SAR":4.4092,
  "SBD":10.0445,
  "SCR":17.3127,
  "SDG":523.7262,
  "SEK":11.1470,
  "SGD":1.4966,
  "SHP":0.8574,
  "SLE":26.4107,
  "SLL":26411.0894,
  "SOS":669.8596,
  "SRD":44.3968,
  "SSP":5532.3825,
  "STN":24.5000,
  "SYP":15119.6076,
  "SZL":20.8676,
  "THB":38.1792,
  "TJS":11.5911,
  "TMT":4.1031,
  "TND":3.3949,
  "TOP":2.7793,
  "TRY":46.8472,
  "TTD":7.9566,
  "TVD":1.7925,
  "TWD":34.2701,
  "TZS":3085.1630,
  "UAH":48.9760,
  "UGX":4209.5770,
  "USD":1.1758,
  "UYU":47.1663,
  "UZS":14887.6661,
  "VES":127.1384,
  "VND":30255.9752,
  "VUV":139.7827,
  "WST":3.1460,
  "XAF":655.9570,
  "XCD":3.1747,
  "XCG":2.1047,
  "XDR":0.8528,
  "XOF":655.9570,
  "XPF":119.3320,
  "YER":284.0399,
  "ZAR":20.8677,
  "ZMW":27.8847,
  "ZWL":31.6222
 }
}