{
 "result":"success",
 "documentation":"https://www.exchangerate-api.com/docs",
 "terms_of_use":"https://www.exchangerate-api.com/terms",
 "time_last_update_unix":1783641601,
 "time_last_update_utc":"Fri, 10 Jul 2026 00:00:01 +0000",
 "time_next_update_unix":1783728001,
 "time_next_update_utc":"Sat, 11 Jul 2026 00:00:01 +0000",
 "base_code":"EUR",
 "conversion_rates":{
  "EUR":1,
  "AED":4.1980,
  "AFN":74.4080,
  "ALL":93.9093,
  "AMD":419.6866,
  "ANG":2.0461,
  "AOA":1082.8860,
  "ARS":1704.2185,
  "AUD":1.6476,
  "AWG":2.0461,
  "AZN":1.9427,
  "BAM":1.9558,
  "BBD":2.2862,
  "BDT":140.8745,
  "BGN":1.9558,
  "BHD":0.4298,
  "BIF":3420.0991,
  "BMD":1.1431,
  "BND":1.4777,
  "BOB":11.3355,
  "BRL":5.8767,
  "BSD":1.1431,
  "BTN":109.0771,
  "BWP":16.0221,
  "BYN":3.2606,
  "BZD":2.2862,
  "CAD":1.6199,
  "CDF":2643.8722,
  "CHF":0.9225,
  "CLF":0.02706,
  "CLP":1069.5426,
  "CNH":7.7699,
  "CNY":7.7726,
  "COP":3819.4859,
  "CRC":519.9142,
  "CUP":27.4339,
  "CVE":110.2650,
  "CZK":24.2532,
  "DJF":203.1491,
  "DKK":7.4637,
  "DOP":67.1847,
  "DZD":152.1735,
  "EGP":56.7107,
  "ERN":17.1462,
  "ETB":185.6939,
  "FJD":2.5507,
  "FKP":0.8528,
  "FOK":7.4637,
  "GBP":0.8528,
  "GEL":3.0099,
  "GGP":0.8528,
  "GHS":13.0901,
  "GIP":0.8528,
  "GMD":84.9266,
  "GNF":10038.7521,
  "GTQ":8.7165,
  "GYD":239.0449,
  "HKD":8.9594,
  "HNL":30.5856,
  "HRK":7.5345,
  "HTG":149.5047,
  "HUF":357.5147,
  "IDR":20676.8193,
  "ILS":3.4549,
  "IMP":0.8528,
  "INR":109.0772,
  "IQD":1496.3191,
  "IRR":1569640.5809,
  "ISK":143.3856,
  "JEP":0.8528,
  "JMD":181.4466,
  "JOD":0.8104,
  "JPY":185.6266,
  "KES":147.6404,
  "KGS":99.9305,
  "KHR":4626.7763,
  "KID":1.6476,
  "KMF":491.9678,
  "KRW":1725.7547,
  "KWD":0.3532,
  "KYD":0.9526,
  "KZT":533.5505,
  "LAK":25453.0964,
  "LBP":102305.5245,
  "LKR":383.0396,
  "LRD":207.2669,
  "LSL":18.6710,
  "LYD":7.3151,
  "MAD":10.6930,
  "MDL":20.0494,
  "MGA":4846.1587,
  "MKD":61.6400,
  "MMK":2402.8763,
  "MNT":4100.7281,
  "MOP":9.2281,
  "MRU":45.5840,
  "MUR":53.8465,
  "MVR":17.6671,
  "MWK":1995.7595,
  "MXN":20.0581,
  "MYR":4.6602,
  "MZN":72.9268,
  "NAD":18.6710,
  "NGN":1561.4387,
  "NIO":42.0227,
  "NOK":11.1185,
  "NPR":174.5234,
  "NZD":1.9868,
  "OMR":0.4395,
  "PAB":1.1431,
  "PEN":3.8895,
  "PGK":5.0205,
  "PHP":70.4320,
  "PKR":317.8142,
  "PLN":4.3240,
  "PYG":6920.3716,
  "QAR":4.1608,
  "RON":5.2351,
  "RSD":117.3527,
  "RUB":87.0714,
  "RWF":1678.4884,
  "SAR":4.2865,
  "SBD":9.1175,
  "SCR":16.3189,
  "SDG":511.0974,
  "SEK":11.0528,
  "SGD":1.4777,
  "SHP":0.8528,
  "SLE":27.8090,
  "SLL":27808.8011,
  "SOS":653.5967,
  "SRD":43.0820,
  "SSP":5388.4025,
  "STN":24.5000,
  "SYP":139.0935,
  "SZL":18.6710,
  "THB":38.1907,
  "TJS":10.5752,
  "TMT":3.9993,
  "TND":3.3687,
  "TOP":2.7292,
  "TRY":53.6672,
  "TTD":8.6549,
  "TVD":1.6476,
  "TWD":36.7417,
  "TZS":2986.3642,
  "UAH":50.8972,
  "UGX":4192.2590,
  "USD":1.1431,
  "UYU":45.9537,
  "UZS":13668.0914,
  "VES":811.4494,
  "VND":29990.3646,
  "VUV":137.0768,
  "WST":3.1245,
  "XAF":655.9570,
  "XCD":3.0863,
  "XCG":2.0461,
  "XDR":0.8410,
  "XOF":655.9570,
  "XPF":119.3320,
  "YER":271.5461,
  "ZAR":18.6721,
  "ZMW":20.7986,
  "ZWG":30.5863,
  "ZWL":30.5863
 }
}