{
 "result":"success",
 "documentation":"https://www.exchangerate-api.com/docs",
 "terms_of_use":"https://www.exchangerate-api.com/terms",
 "time_last_update_unix":1780012801,
 "time_last_update_utc":"Fri, 29 May 2026 00:00:01 +0000",
 "time_next_update_unix":1780099201,
 "time_next_update_utc":"Sat, 30 May 2026 00:00:01 +0000",
 "base_code":"GBP",
 "conversion_rates":{
  "GBP":1,
  "AED":4.9332,
  "AFN":83.7476,
  "ALL":110.1654,
  "AMD":493.0302,
  "ANG":2.4045,
  "AOA":1276.2018,
  "ARS":1895.9074,
  "AUD":1.8793,
  "AWG":2.4045,
  "AZN":2.2773,
  "BAM":2.2565,
  "BBD":2.6866,
  "BDT":164.9049,
  "BGN":2.2565,
  "BHD":0.5051,
  "BIF":4013.0097,
  "BMD":1.3433,
  "BND":1.7152,
  "BOB":9.2657,
  "BRL":6.7789,
  "BSD":1.3433,
  "BTN":128.4010,
  "BWP":18.8606,
  "BYN":3.6741,
  "BZD":2.6866,
  "CAD":1.8544,
  "CDF":3107.8195,
  "CHF":1.0550,
  "CLF":0.03035,
  "CLP":1199.4851,
  "CNH":9.0992,
  "CNY":9.1155,
  "COP":4871.0472,
  "CRC":607.8130,
  "CUP":32.2386,
  "CVE":127.2168,
  "CZK":28.0197,
  "DJF":238.7284,
  "DKK":8.6108,
  "DOP":79.3160,
  "DZD":177.9172,
  "EGP":70.0942,
  "ERN":20.1491,
  "ETB":212.8218,
  "EUR":1.1537,
  "FJD":2.9683,
  "FKP":1.0000,
  "FOK":8.6108,
  "GEL":3.5771,
  "GGP":1.0000,
  "GHS":15.7654,
  "GIP":1.0000,
  "GMD":99.5930,
  "GNF":11763.5856,
  "GTQ":10.2186,
  "GYD":281.9509,
  "HKD":10.5222,
  "HNL":35.6379,
  "HRK":8.6928,
  "HTG":176.4902,
  "HUF":409.1874,
  "IDR":23860.5262,
  "ILS":3.7962,
  "IMP":1.0000,
  "INR":128.4012,
  "IQD":1766.4103,
  "IRR":1797085.4271,
  "ISK":165.2137,
  "JEP":1.0000,
  "JMD":211.2940,
  "JOD":0.9524,
  "JPY":214.0040,
  "KES":173.7947,
  "KGS":117.1951,
  "KHR":5438.6842,
  "KID":1.8797,
  "KMF":567.6013,
  "KRW":2012.7238,
  "KWD":0.4133,
  "KYD":1.1194,
  "KZT":650.5213,
  "LAK":29411.7108,
  "LBP":120223.2280,
  "LKR":440.8954,
  "LRD":244.3681,
  "LSL":21.8398,
  "LYD":8.5887,
  "MAD":12.3291,
  "MDL":23.2208,
  "MGA":5637.0131,
  "MKD":71.2263,
  "MMK":2814.2133,
  "MNT":4790.4035,
  "MOP":10.8392,
  "MRU":53.8975,
  "MUR":63.7322,
  "MVR":20.6904,
  "MWK":2348.6067,
  "MXN":23.2904,
  "MYR":5.3348,
  "MZN":85.7889,
  "NAD":21.8398,
  "NGN":1837.8257,
  "NIO":49.1684,
  "NOK":12.4406,
  "NPR":205.4417,
  "NZD":2.2677,
  "OMR":0.5165,
  "PAB":1.3433,
  "PEN":4.5801,
  "PGK":5.8416,
  "PHP":82.5407,
  "PKR":374.3506,
  "PLN":4.8793,
  "PYG":8219.9666,
  "QAR":4.8895,
  "RON":6.0539,
  "RSD":135.4397,
  "RUB":95.4583,
  "RWF":1973.0794,
  "SAR":5.0373,
  "SBD":10.7135,
  "SCR":19.1183,
  "SDG":602.5364,
  "SEK":12.4576,
  "SGD":1.7152,
  "SHP":1.0000,
  "SLE":33.0192,
  "SLL":33019.1473,
  "SOS":769.7207,
  "SRD":50.3766,
  "SSP":6307.6408,
  "STN":28.2666,
  "SYP":148.3435,
  "SZL":21.8398,
  "THB":43.7822,
  "TJS":12.3424,
  "TMT":4.6892,
  "TND":3.8881,
  "TOP":3.1751,
  "TRY":61.6780,
  "TTD":9.2593,
  "TVD":1.8797,
  "TWD":42.1866,
  "TZS":3526.3493,
  "UAH":59.3217,
  "UGX":5053.7846,
  "USD":1.3433,
  "UYU":53.6438,
  "UZS":16064.5106,
  "VES":737.9587,
  "VND":34868.6821,
  "VUV":158.2762,
  "WST":3.6060,
  "XAF":756.8017,
  "XCD":3.6268,
  "XCG":2.4045,
  "XDR":0.9811,
  "XOF":756.8017,
  "XPF":137.6777,
  "YER":319.8100,
  "ZAR":21.8412,
  "ZMW":24.8913,
  "ZWG":36.0117,
  "ZWL":36.0117
 }
}