{
 "result":"success",
 "documentation":"https://www.exchangerate-api.com/docs",
 "terms_of_use":"https://www.exchangerate-api.com/terms",
 "time_last_update_unix":1764892801,
 "time_last_update_utc":"Fri, 05 Dec 2025 00:00:01 +0000",
 "time_next_update_unix":1764979201,
 "time_next_update_utc":"Sat, 06 Dec 2025 00:00:01 +0000",
 "base_code":"EUR",
 "conversion_rates":{
  "EUR":1,
  "AED":4.2800,
  "AFN":77.3016,
  "ALL":96.6312,
  "AMD":444.7387,
  "ANG":2.0861,
  "AOA":1101.6509,
  "ARS":1689.0786,
  "AUD":1.7634,
  "AWG":2.0861,
  "AZN":1.9840,
  "BAM":1.9558,
  "BBD":2.3308,
  "BDT":142.5387,
  "BGN":1.9558,
  "BHD":0.4382,
  "BIF":3459.0621,
  "BMD":1.1654,
  "BND":1.5101,
  "BOB":8.0748,
  "BRL":6.1859,
  "BSD":1.1654,
  "BTN":104.8289,
  "BWP":16.3574,
  "BYN":3.3969,
  "BZD":2.3308,
  "CAD":1.6264,
  "CDF":2659.1567,
  "CHF":0.9351,
  "CLF":0.02716,
  "CLP":1073.5028,
  "CNH":8.2382,
  "CNY":8.2475,
  "COP":4400.0699,
  "CRC":574.0787,
  "CUP":27.9701,
  "CVE":110.2650,
  "CZK":24.1888,
  "DJF":207.1197,
  "DKK":7.4626,
  "DOP":74.0736,
  "DZD":151.7741,
  "EGP":55.5040,
  "ERN":17.4813,
  "ETB":179.3084,
  "FJD":2.6337,
  "FKP":0.8740,
  "FOK":7.4626,
  "GBP":0.8740,
  "GEL":3.1503,
  "GGP":0.8740,
  "GHS":13.5250,
  "GIP":0.8740,
  "GMD":86.5375,
  "GNF":10155.3746,
  "GTQ":8.9406,
  "GYD":243.8925,
  "HKD":9.0699,
  "HNL":30.7292,
  "HRK":7.5345,
  "HTG":152.4720,
  "HUF":382.5774,
  "IDR":19396.8949,
  "ILS":3.7724,
  "IMP":0.8740,
  "INR":104.8270,
  "IQD":1529.3004,
  "IRR":49528.7042,
  "ISK":148.9884,
  "JEP":0.8740,
  "JMD":187.5389,
  "JOD":0.8263,
  "JPY":180.6348,
  "KES":150.9365,
  "KGS":101.8877,
  "KHR":4688.5132,
  "KID":1.7634,
  "KMF":491.9678,
  "KRW":1717.2028,
  "KWD":0.3574,
  "KYD":0.9712,
  "KZT":586.8076,
  "LAK":25389.6045,
  "LBP":104305.1186,
  "LKR":359.8615,
  "LRD":206.6866,
  "LSL":19.7942,
  "LYD":6.3420,
  "MAD":10.7634,
  "MDL":19.8066,
  "MGA":5126.2071,
  "MKD":61.6560,
  "MMK":2454.1739,
  "MNT":4097.0033,
  "MOP":9.3432,
  "MRU":46.6885,
  "MUR":53.6846,
  "MVR":18.0283,
  "MWK":2034.6888,
  "MXN":21.2590,
  "MYR":4.7952,
  "MZN":74.5329,
  "NAD":19.7942,
  "NGN":1686.3543,
  "NIO":42.9443,
  "NOK":11.7774,
  "NPR":167.7263,
  "NZD":2.0218,
  "OMR":0.4481,
  "PAB":1.1654,
  "PEN":3.9200,
  "PGK":4.9597,
  "PHP":68.8516,
  "PKR":329.1359,
  "PLN":4.2323,
  "PYG":8133.1910,
  "QAR":4.2421,
  "RON":5.0925,
  "RSD":117.4274,
  "RUB":89.9325,
  "RWF":1702.6588,
  "SAR":4.3703,
  "SBD":9.4567,
  "SCR":16.2357,
  "SDG":520.9459,
  "SEK":10.9712,
  "SGD":1.5102,
  "SHP":0.8740,
  "SLE":26.7613,
  "SLL":26761.4260,
  "SOS":664.7892,
  "SRD":44.9340,
  "SSP":5508.4293,
  "STN":24.5000,
  "SYP":12846.9544,
  "SZL":19.7942,
  "THB":37.3380,
  "TJS":10.8293,
  "TMT":4.0852,
  "TND":3.4259,
  "TOP":2.8181,
  "TRY":49.5074,
  "TTD":8.0650,
  "TVD":1.7634,
  "TWD":36.5426,
  "TZS":2825.2880,
  "UAH":49.2711,
  "UGX":4126.4042,
  "USD":1.1654,
  "UYU":45.7330,
  "UZS":13885.1989,
  "VES":297.3778,
  "VND":30438.7904,
  "VUV":142.1283,
  "WST":3.2203,
  "XAF":655.9570,
  "XCD":3.1466,
  "XCG":2.0861,
  "XDR":0.8524,
  "XOF":655.9570,
  "XPF":119.3320,
  "YER":278.2551,
  "ZAR":19.7865,
  "ZMW":26.8752,
  "ZWG":30.4990,
  "ZWL":30.4990
 }
}