{
 "result":"success",
 "documentation":"https://www.exchangerate-api.com/docs",
 "terms_of_use":"https://www.exchangerate-api.com/terms",
 "time_last_update_unix":1783900801,
 "time_last_update_utc":"Mon, 13 Jul 2026 00:00:01 +0000",
 "time_next_update_unix":1783987201,
 "time_next_update_utc":"Tue, 14 Jul 2026 00:00:01 +0000",
 "base_code":"EUR",
 "conversion_rates":{
  "EUR":1,
  "AED":4.1883,
  "AFN":74.0956,
  "ALL":93.7837,
  "AMD":419.3990,
  "ANG":2.0414,
  "AOA":1062.1507,
  "ARS":1700.2828,
  "AUD":1.6432,
  "AWG":2.0414,
  "AZN":1.9416,
  "BAM":1.9558,
  "BBD":2.2809,
  "BDT":140.5692,
  "BGN":1.9558,
  "BHD":0.4288,
  "BIF":3412.8259,
  "BMD":1.1404,
  "BND":1.4741,
  "BOB":11.4386,
  "BRL":5.8439,
  "BSD":1.1404,
  "BTN":108.7735,
  "BWP":15.8984,
  "BYN":3.2703,
  "BZD":2.2809,
  "CAD":1.6153,
  "CDF":2621.2687,
  "CHF":0.9229,
  "CLF":0.02676,
  "CLP":1057.9228,
  "CNH":7.7395,
  "CNY":7.7282,
  "COP":3740.8082,
  "CRC":519.5651,
  "CUP":27.3705,
  "CVE":110.2650,
  "CZK":24.2553,
  "DJF":202.6799,
  "DKK":7.4610,
  "DOP":67.0387,
  "DZD":152.1209,
  "EGP":56.8223,
  "ERN":17.1066,
  "ETB":184.3855,
  "FJD":2.5416,
  "FKP":0.8520,
  "FOK":7.4610,
  "GBP":0.8519,
  "GEL":3.0048,
  "GGP":0.8520,
  "GHS":13.0876,
  "GIP":0.8520,
  "GMD":84.7922,
  "GNF":10033.1151,
  "GTQ":8.7119,
  "GYD":238.7831,
  "HKD":8.9448,
  "HNL":30.5608,
  "HRK":7.5345,
  "HTG":149.3410,
  "HUF":356.6759,
  "IDR":20664.6909,
  "ILS":3.4330,
  "IMP":0.8520,
  "INR":108.8110,
  "IQD":1494.6809,
  "IRR":1570648.6032,
  "ISK":143.3642,
  "JEP":0.8520,
  "JMD":181.2781,
  "JOD":0.8086,
  "JPY":184.6108,
  "KES":147.5935,
  "KGS":99.8825,
  "KHR":4621.7105,
  "KID":1.6430,
  "KMF":491.9678,
  "KRW":1715.7001,
  "KWD":0.3528,
  "KYD":0.9504,
  "KZT":540.6257,
  "LAK":25525.3792,
  "LBP":102069.2662,
  "LKR":382.8011,
  "LRD":207.0552,
  "LSL":18.6475,
  "LYD":7.2995,
  "MAD":10.6691,
  "MDL":19.9965,
  "MGA":4871.7492,
  "MKD":61.6220,
  "MMK":2400.9376,
  "MNT":4079.4537,
  "MOP":9.2128,
  "MRU":45.7476,
  "MUR":53.7419,
  "MVR":17.6553,
  "MWK":1986.8708,
  "MXN":19.9791,
  "MYR":4.6448,
  "MZN":72.6444,
  "NAD":18.6475,
  "NGN":1567.8962,
  "NIO":42.0144,
  "NOK":11.1529,
  "NPR":174.0375,
  "NZD":1.9811,
  "OMR":0.4385,
  "PAB":1.1404,
  "PEN":3.8779,
  "PGK":5.0572,
  "PHP":70.2442,
  "PKR":317.2498,
  "PLN":4.3373,
  "PYG":6923.8672,
  "QAR":4.1512,
  "RON":5.2340,
  "RSD":117.3463,
  "RUB":87.7809,
  "RWF":1674.7940,
  "SAR":4.2766,
  "SBD":9.1019,
  "SCR":16.7748,
  "SDG":510.5378,
  "SEK":11.0360,
  "SGD":1.4742,
  "SHP":0.8520,
  "SLE":27.7465,
  "SLL":27743.9644,
  "SOS":652.8810,
  "SRD":43.0401,
  "SSP":5474.1435,
  "STN":24.5000,
  "SYP":138.9065,
  "SZL":18.6475,
  "THB":38.0435,
  "TJS":10.5577,
  "TMT":3.9972,
  "TND":3.3595,
  "TOP":2.7243,
  "TRY":53.6393,
  "TTD":7.8013,
  "TVD":1.6430,
  "TWD":36.6431,
  "TZS":2994.4991,
  "UAH":50.8507,
  "UGX":4176.3493,
  "USD":1.1405,
  "UYU":45.8861,
  "UZS":13982.4765,
  "VES":823.9426,
  "VND":29885.6528,
  "VUV":136.8333,
  "WST":3.1118,
  "XAF":655.9570,
  "XCD":3.0792,
  "XCG":2.0414,
  "XDR":0.8421,
  "XOF":655.9570,
  "XPF":119.3320,
  "YER":271.3635,
  "ZAR":18.6494,
  "ZMW":20.5756,
  "ZWG":30.5563,
  "ZWL":30.5563
 }
}