{
 "result":"success",
 "documentation":"https://www.exchangerate-api.com/docs",
 "terms_of_use":"https://www.exchangerate-api.com/terms",
 "time_last_update_unix":1764115201,
 "time_last_update_utc":"Wed, 26 Nov 2025 00:00:01 +0000",
 "time_next_update_unix":1764201601,
 "time_next_update_utc":"Thu, 27 Nov 2025 00:00:01 +0000",
 "base_code":"CNY",
 "conversion_rates":{
  "CNY":1,
  "AED":0.5179,
  "AFN":9.3009,
  "ALL":11.8133,
  "AMD":53.7816,
  "ANG":0.2524,
  "AOA":132.9240,
  "ARS":203.4640,
  "AUD":0.2184,
  "AWG":0.2524,
  "AZN":0.2396,
  "BAM":0.2387,
  "BBD":0.2820,
  "BDT":17.2442,
  "BGN":0.2387,
  "BHD":0.05302,
  "BIF":416.7177,
  "BMD":0.1410,
  "BND":0.1835,
  "BOB":0.9766,
  "BRL":0.7583,
  "BSD":0.1410,
  "BTN":12.5395,
  "BWP":2.0438,
  "BYN":0.4520,
  "BZD":0.2820,
  "CAD":0.1988,
  "CDF":314.3686,
  "CHF":0.1139,
  "CLF":0.003350,
  "CLP":132.4266,
  "CNH":0.9991,
  "COP":534.5658,
  "CRC":70.4699,
  "CUP":3.3844,
  "CVE":13.4575,
  "CZK":2.9507,
  "DJF":25.0617,
  "DKK":0.9105,
  "DOP":8.8880,
  "DZD":18.4139,
  "EGP":6.7419,
  "ERN":2.1153,
  "ETB":21.5585,
  "EUR":0.1220,
  "FJD":0.3230,
  "FKP":0.1072,
  "FOK":0.9105,
  "GBP":0.1072,
  "GEL":0.3814,
  "GGP":0.1072,
  "GHS":1.5810,
  "GIP":0.1072,
  "GMD":10.4599,
  "GNF":1228.9448,
  "GTQ":1.0794,
  "GYD":29.5036,
  "HKD":1.0966,
  "HNL":3.7087,
  "HRK":0.9196,
  "HTG":18.4514,
  "HUF":46.7639,
  "IDR":2347.4178,
  "ILS":0.4617,
  "IMP":0.1072,
  "INR":12.5395,
  "IQD":184.5902,
  "IRR":5990.6942,
  "ISK":17.9361,
  "JEP":0.1072,
  "JMD":22.6244,
  "JOD":0.09998,
  "JPY":22.0367,
  "KES":18.2683,
  "KGS":12.3351,
  "KHR":564.3341,
  "KID":0.2184,
  "KMF":60.0431,
  "KRW":207.8570,
  "KWD":0.04326,
  "KYD":0.1175,
  "KZT":73.0691,
  "LAK":3068.6479,
  "LBP":12621.0477,
  "LKR":43.3765,
  "LRD":25.1827,
  "LSL":2.4328,
  "LYD":0.7712,
  "MAD":1.3070,
  "MDL":2.4182,
  "MGA":631.8612,
  "MKD":7.5197,
  "MMK":295.7114,
  "MNT":501.7561,
  "MOP":1.1295,
  "MRU":5.6173,
  "MUR":6.4939,
  "MVR":2.1759,
  "MWK":245.6652,
  "MXN":2.6103,
  "MYR":0.5832,
  "MZN":8.9761,
  "NAD":2.4328,
  "NGN":205.3077,
  "NIO":5.1863,
  "NOK":1.4438,
  "NPR":20.0632,
  "NZD":0.2516,
  "OMR":0.05422,
  "PAB":0.1410,
  "PEN":0.4764,
  "PGK":0.5967,
  "PHP":8.2850,
  "PKR":39.7646,
  "PLN":0.5154,
  "PYG":985.4826,
  "QAR":0.5133,
  "RON":0.6215,
  "RSD":14.3211,
  "RUB":11.0497,
  "RWF":205.6056,
  "SAR":0.5288,
  "SBD":1.1493,
  "SCR":1.9730,
  "SDG":63.3999,
  "SEK":1.3482,
  "SGD":0.1835,
  "SHP":0.1072,
  "SLE":3.3001,
  "SLL":3300.1139,
  "SOS":80.4352,
  "SRD":5.3965,
  "SSP":665.6774,
  "STN":2.9901,
  "SYP":1551.8482,
  "SZL":2.4328,
  "THB":4.5514,
  "TJS":1.3079,
  "TMT":0.4936,
  "TND":0.4163,
  "TOP":0.3377,
  "TRY":5.9809,
  "TTD":0.9547,
  "TVD":0.2184,
  "TWD":4.4228,
  "TZS":345.5030,
  "UAH":5.9798,
  "UGX":508.6861,
  "USD":0.1410,
  "UYU":5.6105,
  "UZS":1696.6586,
  "VES":34.3835,
  "VND":3717.4721,
  "VUV":17.2897,
  "WST":0.3938,
  "XAF":80.0574,
  "XCD":0.3807,
  "XCG":0.2524,
  "XDR":0.1040,
  "XOF":80.0574,
  "XPF":14.5641,
  "YER":33.5945,
  "ZAR":2.4328,
  "ZMW":3.2492,
  "ZWG":3.7070,
  "ZWL":3.7070
 }
}