{
 "result":"success",
 "documentation":"https://www.exchangerate-api.com/docs",
 "terms_of_use":"https://www.exchangerate-api.com/terms",
 "time_last_update_unix":1768953601,
 "time_last_update_utc":"Wed, 21 Jan 2026 00:00:01 +0000",
 "time_next_update_unix":1769040001,
 "time_next_update_utc":"Thu, 22 Jan 2026 00:00:01 +0000",
 "base_code":"AUD",
 "conversion_rates":{
  "AUD":1,
  "AED":2.4728,
  "AFN":44.3673,
  "ALL":55.5082,
  "AMD":255.0281,
  "ANG":1.2053,
  "AOA":630.0682,
  "ARS":977.8353,
  "AWG":1.2053,
  "AZN":1.1442,
  "BAM":1.1232,
  "BBD":1.3466,
  "BDT":82.3312,
  "BGN":1.1905,
  "BHD":0.2532,
  "BIF":1997.2816,
  "BMD":0.6733,
  "BND":0.8641,
  "BOB":4.6593,
  "BRL":3.6219,
  "BSD":0.6733,
  "BTN":61.3349,
  "BWP":9.3616,
  "BYN":1.9476,
  "BZD":1.3466,
  "CAD":0.9312,
  "CDF":1535.2239,
  "CHF":0.5321,
  "CLF":0.01513,
  "CLP":597.9261,
  "CNH":4.6847,
  "CNY":4.6839,
  "COP":2464.5860,
  "CRC":327.9787,
  "CUP":16.1598,
  "CVE":63.3220,
  "CZK":13.9671,
  "DJF":119.6639,
  "DKK":4.2843,
  "DOP":42.7350,
  "DZD":87.3821,
  "EGP":31.9505,
  "ERN":10.0999,
  "ETB":105.0128,
  "EUR":0.5742,
  "FJD":1.5298,
  "FKP":0.5006,
  "FOK":4.2843,
  "GBP":0.5006,
  "GEL":1.8137,
  "GGP":0.5006,
  "GHS":7.3044,
  "GIP":0.5006,
  "GMD":49.8122,
  "GNF":5889.2586,
  "GTQ":5.1565,
  "GYD":140.8077,
  "HKD":5.2514,
  "HNL":17.7388,
  "HRK":4.3268,
  "HTG":88.1405,
  "HUF":221.2701,
  "IDR":11420.8314,
  "ILS":2.1348,
  "IMP":0.5006,
  "INR":61.3360,
  "IQD":882.9185,
  "IRR":28273.3365,
  "ISK":83.8463,
  "JEP":0.5006,
  "JMD":106.0054,
  "JOD":0.4774,
  "JPY":106.3762,
  "KES":86.7751,
  "KGS":58.8497,
  "KHR":2706.8421,
  "KID":1.0000,
  "KMF":282.5228,
  "KRW":995.1025,
  "KWD":0.2065,
  "KYD":0.5611,
  "KZT":342.2200,
  "LAK":14592.9012,
  "LBP":60262.5292,
  "LKR":208.2862,
  "LRD":122.4996,
  "LSL":11.0616,
  "LYD":3.6574,
  "MAD":6.1808,
  "MDL":11.4681,
  "MGA":3070.4478,
  "MKD":35.5045,
  "MMK":1411.6532,
  "MNT":2375.8956,
  "MOP":5.4094,
  "MRU":26.9514,
  "MUR":31.0879,
  "MVR":10.4034,
  "MWK":1174.0645,
  "MXN":11.8603,
  "MYR":2.7293,
  "MZN":43.0042,
  "NAD":11.0616,
  "NGN":954.2253,
  "NIO":24.7552,
  "NOK":6.7294,
  "NPR":98.1358,
  "NZD":1.1545,
  "OMR":0.2589,
  "PAB":0.6733,
  "PEN":2.2608,
  "PGK":2.8721,
  "PHP":39.9919,
  "PKR":188.4195,
  "PLN":2.4272,
  "PYG":4484.2910,
  "QAR":2.4509,
  "RON":2.9234,
  "RSD":67.4592,
  "RUB":52.4815,
  "RWF":982.9432,
  "SAR":2.5250,
  "SBD":5.4011,
  "SCR":9.5532,
  "SDG":300.7602,
  "SEK":6.1461,
  "SGD":0.8641,
  "SHP":0.5006,
  "SLE":16.2593,
  "SLL":16259.3219,
  "SOS":383.8060,
  "SRD":25.8377,
  "SSP":3177.3188,
  "STN":14.0696,
  "SYP":75.5996,
  "SZL":11.0616,
  "THB":20.9147,
  "TJS":6.2594,
  "TMT":2.3562,
  "TND":1.9421,
  "TOP":1.6055,
  "TRY":29.1348,
  "TTD":4.5641,
  "TVD":1.0000,
  "TWD":21.3545,
  "TZS":1712.7599,
  "UAH":29.1065,
  "UGX":2331.9600,
  "USD":0.6733,
  "UYU":25.9142,
  "UZS":8169.9450,
  "VES":233.8187,
  "VND":17618.4185,
  "VUV":81.2350,
  "WST":1.8499,
  "XAF":376.6971,
  "XCD":1.8180,
  "XCG":1.2053,
  "XDR":0.4880,
  "XOF":376.6971,
  "XPF":68.5289,
  "YER":160.4736,
  "ZAR":11.0607,
  "ZMW":13.5910,
  "ZWG":17.2533,
  "ZWL":17.2533
 }
}